shitlint/__init__.py
shitlint/cli.py
shitlint/core.py
shitlint-0.0.1.dist-info/METADATA
shitlint-0.0.1.dist-info/WHEEL
shitlint-0.0.1.dist-info/entry_points.txt
shitlint-0.0.1.dist-info/RECORD
