Metadata-Version: 2.3
Name: shitlint
Version: 0.0.1
Summary: Your code is shit. Here's why.
License: MIT
Keywords: shitlint,shit,lint,your,code,is,bad,and,you,should,feel,bad,brutal,honest,roast
Author: Tyson Chan
Author-email: tyson.chan@proton.me
Requires-Python: >=3.10,<4.0
Classifier: Development Status :: 3 - Alpha
Classifier: Environment :: Console
Classifier: Intended Audience :: Developers
Classifier: License :: OSI Approved :: MIT License
Classifier: Operating System :: OS Independent
Classifier: Programming Language :: Python :: 3
Classifier: Programming Language :: Python :: 3.10
Classifier: Programming Language :: Python :: 3.11
Classifier: Programming Language :: Python :: 3.12
Classifier: Programming Language :: Python :: 3.13
Classifier: Topic :: Software Development :: Libraries :: Python Modules
Classifier: Topic :: Software Development :: Quality Assurance
Requires-Dist: anthropic (>=0.25.0,<0.26.0)
Requires-Dist: click (>=8.0.0,<9.0.0)
Requires-Dist: openai (>=1.0.0,<2.0.0)
Requires-Dist: pathspec (>=0.11.0,<0.12.0)
Requires-Dist: pydantic (>=2.0.0,<3.0.0)
Requires-Dist: rich (>=13.0.0,<14.0.0)
Requires-Dist: tree-sitter (>=0.20.0,<0.21.0)
Requires-Dist: tree-sitter-go (>=0.20.0,<0.21.0)
Requires-Dist: tree-sitter-javascript (>=0.20.0,<0.21.0)
Requires-Dist: tree-sitter-python (>=0.20.0,<0.21.0)
Requires-Dist: tree-sitter-typescript (>=0.20.0,<0.21.0)
Requires-Dist: watchdog (>=3.0.0,<4.0.0)
Project-URL: Homepage, https://github.com/iteebz/shitlint
Project-URL: Repository, https://github.com/iteebz/shitlint
